{"stats":{"minecraft:picked_up":{"minecraft:iron_chestplate":1,"minecraft:flower_pot":4,"minecraft:anvil":2,"securitycraft:reinforced_sand":12,"minecraft:lead":2,"minecraft:stone_slab":11,"minecraft:oak_stairs":2,"betteranimalsplus:venisonraw":8,"minecraft:enchanted_book":8,"minecraft:brewing_stand":2,"iceandfire:manuscript":3,"minecraft:string":201,"minecraft:dark_oak_trapdoor":2,"minecraft:beetroot":451,"bosses_of_mass_destruction:soul_star":1,"travelersbackpack:enderman":1,"minecraft:spruce_planks":141,"minecraft:coal_block":57,"elevatorid:elevator_blue":8,"minecraft:composter":8,"minecraft:tropical_fish":19,"minecraft:iron_block":3,"minecraft:cyan_terracotta":512,"dawnoftimebuilder:maple_red_sapling":8,"mcwdoors:garage_white_door":8,"minecraft:iron_bars":7,"minecraft:snowball":26,"minecraft:birch_log":96,"minecraft:feather":10,"minecraft:birch_slab":8,"minecraft:iron_door":3,"minecraft:water_bucket":2,"rechiseled:stone_smooth_tiles":4,"minecraft:smoker":2,"minecraft:flint":16,"gobber2:gobber2_gooey_bread_nether":2,"minecraft:lantern":78,"securitycraft:reinforced_stone_button":8,"rechiseled:granite_rotated_bricks_connecting":8,"dawnoftimebuilder:rice":40,"rechiseled:chisel":4,"securitycraft:reinforced_blue_stained_glass":729,"rechiseled:stone_smooth_tiles_connecting":4,"additional_lights:fire_for_fire_pit_s":2,"securitycraft:mine":4,"additional_lights:al_torch_stone_bricks":9,"betteranimalsplus:wolf_pelt_brown":3,"minecraft:ink_sac":40,"minecraft:dark_oak_log":237,"securitycraft:universal_block_remover":3,"minecraft:polished_andesite":2,"minecraft:lever":14,"rechiseled:cobblestone_rotated_bricks":27,"minecraft:granite":512,"minecraft:bread":40,"immersive_armors:divine_helmet":1,"piratesandlootersreborn:rom":1,"minecraft:spruce_leaves":18,"minecraft:crafting_table":11,"minecraft:clay_ball":194,"gravestone:obituary":39,"dawnoftimebuilder:boxwood_tall_hedge":18,"minecraft:flint_and_steel":2,"minecraft:white_carpet":1,"minecraft:iron_shovel":1,"minecraft:glass_pane":4,"minecraft:cracked_stone_bricks":4,"dawnoftimebuilder:cypress":70,"minecraft:beef":15,"valhelsia_structures:doused_torch":23,"minecraft:iron_nugget":17,"minecraft:poppy":1,"minecraft:minecart":2,"securitycraft:reinforced_polished_diorite":1154,"minecraft:chest":17,"minecraft:birch_sapling":15,"minecraft:piston":12,"minecraft:sandstone":10,"mcwfurnitures:spruce_stool_chair":2,"minecraft:stone":171,"minecraft:spruce_fence":4,"minecraft:carrot":1198,"minecraft:redstone":902,"minecraft:tnt":21,"minecraft:beetroot_seeds":1613,"minecraft:shears":2,"additional_lights:fire_pit_l_smooth_stone":7,"minecraft:hay_block":4,"artifacts:pocket_piston":9,"minecraft:gold_ingot":53,"minecraft:totem_of_undying":3,"minecraft:mutton":17,"minecraft:white_wool":20,"minecraft:rail":16,"rechiseled:andesite_bricks":1,"rechiseled:stone_small_tiles_connecting":8,"minecraft:red_mushroom":7,"minecraft:filled_map":1,"minecraft:oak_log":47,"minecraft:lily_pad":3,"iceandfire:pixie_jar_1":2,"iceandfire:pixie_jar_3":2,"minecraft:white_banner":3,"minecraft:apple":15,"minecraft:stone_bricks":17,"iceandfire:pixie_jar_empty":2,"minecraft:kelp":16,"betteranimalsplus:antler":2,"minecraft:iron_ore":936,"minecraft:glass_bottle":1,"minecraft:gray_bed":2,"minecraft:iron_sword":21,"travelersbackpack:blank_upgrade":2,"elevatorid:elevator_white":11,"minecraft:polished_andesite_stairs":1,"minecraft:dark_oak_slab":8,"rechiseled:birch_planks_mosaic":7,"minecraft:gravel":270,"minecraft:dead_fire_coral_block":1,"minecraft:birch_stairs":5,"minecraft:spruce_sapling":81,"dawnoftimebuilder:boxwood_bush":16,"minecraft:spruce_log":280,"travelersbackpack:standard":12,"minecraft:red_stained_glass":2,"minecraft:slime_ball":7,"minecraft:polished_diorite":56,"minecraft:stone_axe":1,"betteranimalsplus:eel_meat_cooked":6,"minecraft:painting":33,"minecraft:warped_roots":1,"securitycraft:keypad":1,"minecraft:baked_potato":21,"minecraft:melon_seeds":3,"minecraft:stripped_dark_oak_log":1,"minecraft:hopper":1,"minecraft:ender_pearl":6,"minecraft:wheat":317,"betteranimalsplus:calamari_raw":9,"securitycraft:keypad_item":12,"minecraft:redstone_block":17,"dawnoftimebuilder:spruce_planks_edge":9,"travelersbackpack:spider":3,"minecraft:smooth_stone_slab":6,"piratesandlootersreborn:coconut":3,"minecraft:iron_leggings":2,"minecraft:experience_bottle":12,"minecraft:zombie_head":4,"minecraft:sea_pickle":10,"minecraft:smooth_stone":2,"minecraft:comparator":2,"minecraft:rose_bush":2,"minecraft:redstone_torch":19,"minecraft:cobblestone_slab":15,"minecraft:iron_pickaxe":2,"minecraft:iron_boots":2,"minecraft:furnace":13,"minecraft:tipped_arrow":11,"iceandfire:pixie_dust":8,"minecraft:stick":109,"betteranimalsplus:blackbearhead_black":1,"minecraft:torch":487,"storagedrawers:spruce_full_drawers_4":9,"minecraft:porkchop":11,"minecraft:diorite":1485,"minecraft:blue_stained_glass":24,"minecraft:rotten_flesh":210,"glass_doors_and_trapdoors:black_stained_glass_trapdoor":26,"artifacts:panic_necklace":4,"minecraft:obsidian":40,"rechiseled:stone_small_tiles":2,"minecraft:cod":3,"betteranimalsplus:goose_egg":6,"minecraft:cobblestone":9471,"minecraft:repeater":33,"minecraft:andesite":575,"minecraft:black_bed":12,"minecraft:potato":2400,"gobber2:gobber2_ore":50,"minecraft:lapis_lazuli":459,"minecraft:dirt":2747,"minecraft:name_tag":1,"minecraft:leather_boots":2,"minecraft:glass":17,"travelersbackpack:bookshelf":2,"minecraft:bone":369,"rechiseled:stone_small_bricks_connecting":105,"minecraft:bow":6,"gobber2:gobber2_gooey_beef":1,"minecraft:wheat_seeds":923,"rechiseled:granite_squares_connecting":8,"minecraft:powered_rail":4,"minecraft:prismarine":2,"minecraft:oak_planks":6,"minecraft:stone_hoe":2,"gobber2:gobber2_gooey_bread":2,"minecraft:cooked_porkchop":1,"securitycraft:dirt_mine":4,"minecraft:poisonous_potato":21,"minecraft:sand":1481,"minecraft:dead_bush":1,"minecraft:grass_block":1,"minecraft:lily_of_the_valley":2,"minecraft:spectral_arrow":2,"minecraft:mossy_cobblestone":1,"minecraft:dark_prismarine":1,"travelersbackpack:white_sleeping_bag":3,"minecraft:diamond":18,"minecraft:spruce_boat":16,"waystones:waystone":2,"minecraft:bone_meal":1,"rechiseled:stone_smooth_brick_paving":6,"mcwdoors:garage_black_door":31,"minecraft:spruce_sign":10,"minecraft:emerald":33,"securitycraft:reinforced_polished_diorite_stairs":58,"rechiseled:birch_planks_beams_connecting":10,"minecraft:oak_sapling":29,"gobber2:gobber2_goo":6,"minecraft:chicken":2,"minecraft:ladder":39,"dawnoftimebuilder:commelina":2,"minecraft:brown_mushroom":4,"piratesandlootersreborn:illager_silver_bar":3,"minecraft:gold_block":2,"mowziesmobs:glowing_jelly":2,"minecraft:shield":2,"immersive_armors:warrior_boots":1,"minecraft:stone_stairs":2,"minecraft:iron_axe":1,"artifacts:feral_claws":6,"minecraft:item_frame":4,"minecraft:sugar_cane":449,"minecraft:spruce_trapdoor":1,"minecraft:phantom_membrane":1,"minecraft:dark_oak_sapling":29,"immersive_armors:robe_boots":1,"minecraft:stone_button":1,"minecraft:iron_horse_armor":2,"minecraft:arrow":153,"minecraft:saddle":5,"securitycraft:keypad_door_item":2,"minecraft:skeleton_skull":1,"valhelsia_structures:spruce_post":1,"gobber2:gobber2_ingot":1,"minecraft:salmon":1,"storagedrawers:upgrade_template":3,"minecraft:leather":27,"minecraft:birch_planks":9,"iceandfire:pixie_jar_2":3,"minecraft:gunpowder":69,"minecraft:cobblestone_stairs":1,"glass_doors_and_trapdoors:glass_trapdoor":7,"minecraft:red_carpet":8,"rechiseled:cobblestone_chiseled_border_connecting":142,"minecraft:iron_ingot":277,"storagedrawers:spruce_half_drawers_4":3,"securitycraft:universal_block_reinforcer_lvl1":1,"minecraft:stripped_oak_wood":1,"minecraft:book":8,"minecraft:oak_slab":2,"minecraft:pumpkin":7,"rechiseled:birch_planks_rotated_bricks":1,"minecraft:blast_furnace":5,"rechiseled:dirt_blobs_connecting":3,"minecraft:gold_ore":146,"artifacts:scarf_of_invisibility":1,"minecraft:spider_eye":10,"dawnoftimebuilder:paper_folding_screen":7,"betteranimalsplus:eel_meat_raw":33,"immersive_armors:wooden_chestplate":1,"minecraft:mossy_cobblestone_stairs":1,"minecraft:terracotta":2,"securitycraft:door_indestructible_iron_item":1,"minecraft:coal":2133,"rechiseled:granite_brick_paving_connecting":131},"minecraft:mined":{"valhelsia_structures:doused_torch":4,"minecraft:obsidian":1,"minecraft:granite":495,"minecraft:coal_block":38,"additional_lights:al_wall_torch_stone_bricks":7,"minecraft:bubble_coral_block":2,"minecraft:hopper":1,"glass_doors_and_trapdoors:black_stained_glass_trapdoor":26,"glass_doors_and_trapdoors:glass_trapdoor":7,"minecraft:spawner":12,"minecraft:tall_seagrass":82,"gobber2:gobber2_ore":50,"minecraft:mossy_cobblestone_stairs":1,"dawnoftimebuilder:cypress":6,"minecraft:dark_oak_trapdoor":2,"minecraft:fire":4,"rechiseled:stone_small_bricks_connecting":105,"dawnoftimebuilder:boxwood_bush":13,"minecraft:oak_stairs":2,"additional_lights:al_torch_stone_bricks":1,"minecraft:iron_block":2,"minecraft:piston_head":9,"valhelsia_structures:glazed_jar":1,"minecraft:brown_mushroom":4,"minecraft:kelp_plant":22,"minecraft:smoker":2,"rechiseled:birch_planks_beams_connecting":10,"rechiseled:granite_rotated_bricks_connecting":8,"minecraft:torch":127,"minecraft:blast_furnace":5,"minecraft:polished_andesite_stairs":1,"minecraft:spruce_wall_sign":5,"valhelsia_structures:spruce_post":1,"rechiseled:stone_small_tiles":2,"minecraft:sugar_cane":125,"mcwdoors:garage_black_door":31,"minecraft:skeleton_skull":1,"storagedrawers:spruce_half_drawers_4":3,"minecraft:repeater":24,"dawnoftimebuilder:maple_red_sapling_flower_pot":1,"minecraft:wheat":216,"minecraft:black_bed":10,"dawnoftimebuilder:paper_folding_screen":7,"minecraft:grass":28,"minecraft:red_mushroom_block":4,"minecraft:piston":3,"minecraft:dark_prismarine":1,"rechiseled:dirt_blobs_connecting":3,"minecraft:mossy_cobblestone":4,"minecraft:dark_oak_log":240,"dawnoftimebuilder:spruce_planks_edge":9,"minecraft:spruce_fence":6,"minecraft:redstone_wire":107,"additional_lights:fire_pit_l_smooth_stone":7,"travelersbackpack:bookshelf":2,"minecraft:kelp":8,"minecraft:horn_coral_wall_fan":1,"minecraft:redstone_ore":179,"minecraft:andesite":576,"minecraft:potatoes":355,"minecraft:cobblestone_slab":8,"minecraft:vine":6,"minecraft:rail":5,"minecraft:brain_coral_wall_fan":1,"minecraft:fire_coral_block":5,"valhelsia_structures:stone":4,"minecraft:birch_stairs":5,"rechiseled:stone_smooth_brick_paving":6,"minecraft:redstone_block":15,"minecraft:comparator":1,"minecraft:brown_carpet":8,"mcwfurnitures:spruce_stool_chair":2,"minecraft:emerald_ore":2,"valhelsia_structures:black_glazed_jar":1,"additional_lights:fire_for_fire_pit_l":2,"minecraft:tall_grass":7,"minecraft:diorite":1496,"elevatorid:elevator_blue":8,"rechiseled:granite_squares_connecting":8,"minecraft:white_carpet":1,"minecraft:spruce_log":214,"minecraft:birch_leaves":11,"securitycraft:dirt_mine":3,"additional_lights:fire_for_fire_pit_s":1,"minecraft:zombie_head":2,"minecraft:gravel":126,"minecraft:cobweb":65,"minecraft:stone_bricks":16,"minecraft:gold_ore":145,"minecraft:fern":1,"securitycraft:mine":2,"minecraft:spruce_planks":20,"minecraft:farmland":48,"minecraft:brewing_stand":1,"minecraft:spruce_trapdoor":2,"dawnoftimebuilder:boxwood_tall_hedge":18,"minecraft:grass_block":1138,"gobber2:gobber2_lucky_block":6,"minecraft:polished_diorite":16,"minecraft:composter":9,"minecraft:iron_ore":897,"minecraft:anvil":2,"minecraft:iron_bars":7,"minecraft:brain_coral_block":7,"rechiseled:stone_small_tiles_connecting":8,"minecraft:cyan_terracotta":265,"minecraft:clay":30,"minecraft:poppy":1,"minecraft:potted_warped_roots":1,"minecraft:chest":16,"minecraft:cobblestone":367,"minecraft:prismarine":3,"minecraft:oak_planks":4,"rechiseled:birch_planks_mosaic":7,"minecraft:iron_door":1,"minecraft:wall_torch":208,"minecraft:seagrass":93,"minecraft:stone_stairs":2,"valhelsia_structures:bone_pile":2,"minecraft:dark_oak_slab":3,"minecraft:birch_log":95,"rechiseled:stone_smooth_tiles_connecting":4,"rechiseled:birch_planks_rotated_bricks":1,"rechiseled:cobblestone_chiseled_border_connecting":114,"minecraft:tnt":7,"dawnoftimebuilder:commelina":2,"minecraft:smooth_stone_slab":2,"minecraft:oak_log":51,"minecraft:beetroots":238,"minecraft:sand":1445,"minecraft:dirt":1516,"minecraft:oak_leaves":52,"minecraft:diamond_ore":17,"minecraft:dark_oak_leaves":1,"minecraft:red_stained_glass":3,"minecraft:ladder":45,"minecraft:lever":6,"gravestone:gravestone":52,"mcwdoors:garage_white_door":8,"minecraft:tube_coral_wall_fan":2,"travelersbackpack:white_sleeping_bag":4,"minecraft:birch_slab":8,"minecraft:spruce_leaves":58,"minecraft:sandstone":10,"minecraft:large_fern":16,"minecraft:hay_block":3,"minecraft:furnace":14,"minecraft:carrots":267,"rechiseled:granite_brick_paving_connecting":131,"minecraft:gold_block":2,"minecraft:bookshelf":1,"minecraft:lantern":43,"minecraft:stone":9071,"valhelsia_structures:doused_wall_torch":19,"minecraft:redstone_wall_torch":14,"iceandfire:pixie_jar_empty":2,"rechiseled:stone_smooth_tiles":4,"travelersbackpack:standard":5,"minecraft:crafting_table":11,"minecraft:rose_bush":2,"minecraft:stone_slab":6,"valhelsia_structures:big_cyan_glazed_jar":2,"minecraft:lapis_ore":68,"valhelsia_structures:cyan_glazed_jar":1,"iceandfire:pixie_jar_2":1,"minecraft:sea_pickle":4,"minecraft:redstone_torch":5,"minecraft:gray_bed":1,"elevatorid:elevator_white":10,"minecraft:coal_ore":1238,"minecraft:bubble_coral_wall_fan":1,"storagedrawers:spruce_full_drawers_4":9,"minecraft:cracked_stone_bricks":2,"minecraft:terracotta":1,"minecraft:polished_andesite":2},"minecraft:killed_by":{"minecraft:zombie_villager":1,"minecraft:zombie":4,"betteranimalsplus:feralwolf":1,"betteranimalsplus:shark":3,"minecraft:creeper":5,"minecraft:drowned":2,"minecraft:cave_spider":2,"minecraft:witch":1,"minecraft:player":8,"minecraft:skeleton":18},"minecraft:broken":{"minecraft:iron_boots":10,"minecraft:iron_chestplate":8,"minecraft:iron_leggings":10,"minecraft:iron_sword":5,"securitycraft:universal_block_reinforcer_lvl1":5,"minecraft:iron_hoe":1,"immersive_armors:wooden_chestplate":1,"minecraft:chainmail_helmet":1,"minecraft:stone_hoe":1,"minecraft:shield":3,"minecraft:iron_axe":3,"minecraft:iron_pickaxe":51,"minecraft:iron_helmet":8,"minecraft:iron_shovel":14,"minecraft:stone_pickaxe":1,"minecraft:stone_shovel":4,"dawnoftimebuilder:iron_plate_armor_head":1},"minecraft:killed":{"minecraft:cave_spider":9,"minecraft:zombie_horse":1,"minecraft:skeleton":82,"betteranimalsplus:octopus":4,"minecraft:chicken":1,"betteranimalsplus:goose":5,"betteranimalsplus:deer":3,"minecraft:salmon":1,"minecraft:pillager":14,"minecraft:zombie":138,"piratesandlootersreborn:pirate_skeleton_bomber":1,"whisperwoods:moth":1,"minecraft:cow":8,"piratesandlootersreborn:rozbitek":21,"betteranimalsplus:eel_saltwater":4,"betteranimalsplus:barracuda":3,"betteranimalsplus:lamprey":11,"whisperwoods:zotzpyre":5,"minecraft:enderman":2,"minecraft:witch":1,"minecraft:spider":17,"piratesandlootersreborn:hgt":8,"whisperwoods:wisp":1,"minecraft:pig":4,"minecraft:zombie_villager":2,"minecraft:creeper":19,"minecraft:sheep":5,"mowziesmobs:lantern":1,"minecraft:stray":19,"piratesandlootersreborn:spader_pirate_skeleton":1,"iceandfire:pixie":8,"betteranimalsplus:boar":3,"minecraft:slime":10,"minecraft:phantom":5,"minecraft:drowned":23,"betteranimalsplus:piranha":2,"whisperwoods:hidebehind":1,"minecraft:squid":9,"betteranimalsplus:feralwolf":3,"betteranimalsplus:eel_freshwater":1,"betteranimalsplus:crab":1},"minecraft:crafted":{"minecraft:black_dye":15,"betteranimalsplus:venisoncooked":7,"minecraft:smooth_stone":59,"minecraft:birch_slab":6,"minecraft:diamond_shovel":1,"minecraft:lever":6,"securitycraft:keypad_item":1,"valhelsia_structures:spruce_post":2,"minecraft:cooked_mutton":9,"minecraft:glass":801,"minecraft:repeater":76,"additional_lights:fire_for_fire_pit_s":2,"minecraft:iron_door":3,"mcwfurnitures:spruce_coffee_table":6,"minecraft:flower_pot":4,"mcwfurnitures:spruce_end_table":6,"minecraft:blue_stained_glass":664,"travelersbackpack:bookshelf":3,"gobber2:gobber2_ingot":6,"minecraft:emerald":50,"minecraft:cooked_porkchop":11,"travelersbackpack:standard":1,"minecraft:smithing_table":3,"gobber2:gobber2_rod":2,"storagedrawers:spruce_half_drawers_4":4,"valhelsia_structures:big_black_glazed_jar":1,"minecraft:painting":4,"valhelsia_structures:big_red_glazed_jar":1,"minecraft:stone_slab":30,"minecraft:iron_pickaxe":50,"minecraft:iron_block":7,"minecraft:gold_ingot":250,"betteranimalsplus:eel_meat_cooked":27,"betteranimalsplus:fried_egg":6,"storagedrawers:drawer_key":2,"elevatorid:elevator_blue":3,"minecraft:composter":6,"minecraft:birch_stairs":4,"storagedrawers:upgrade_template":36,"mcwdoors:garage_white_door":18,"securitycraft:iron_mine":1,"minecraft:stone_shovel":5,"minecraft:iron_nugget":297,"dawnoftimebuilder:red_paper_lantern":18,"storagedrawers:spruce_full_drawers_4":44,"mcwfurnitures:spruce_glass_table":2,"minecraft:red_terracotta":8,"minecraft:bone_meal":195,"minecraft:spruce_fence":15,"travelersbackpack:blank_upgrade":4,"travelersbackpack:gold_tier_upgrade":2,"gobber2:gobber2_glob":50,"minecraft:terracotta":17,"minecraft:lantern":36,"travelersbackpack:white_sleeping_bag":1,"minecraft:polished_diorite":888,"minecraft:ladder":39,"securitycraft:universal_block_remover":4,"minecraft:spruce_slab":48,"minecraft:stone_pickaxe":1,"minecraft:spruce_boat":3,"minecraft:redstone_block":6,"minecraft:dark_oak_planks":816,"additional_lights:al_torch_stone_bricks":44,"travelersbackpack:spider":1,"minecraft:wheat":27,"securitycraft:portable_radar":4,"minecraft:enchanting_table":1,"securitycraft:taser":1,"iceandfire:pixie_jar_empty":4,"securitycraft:reinforced_polished_diorite_stairs":60,"minecraft:red_stained_glass":24,"securitycraft:door_indestructible_iron_item":1,"dawnoftimebuilder:boxwood_tall_hedge":48,"minecraft:black_stained_glass_pane":80,"minecraft:writable_book":1,"minecraft:iron_shovel":15,"minecraft:iron_leggings":8,"valhelsia_structures:cyan_glazed_jar":1,"minecraft:brick":28,"minecraft:oak_planks":80,"securitycraft:mine":15,"minecraft:cobblestone_slab":12,"minecraft:dark_oak_boat":1,"valhelsia_structures:big_cyan_glazed_jar":2,"minecraft:stone":929,"minecraft:heavy_weighted_pressure_plate":2,"securitycraft:laser_block":5,"minecraft:hopper":16,"minecraft:bow":1,"minecraft:iron_boots":9,"minecraft:chest":89,"minecraft:stone_hoe":3,"minecraft:stone_bricks":64,"mcwdoors:garage_black_door":8,"securitycraft:keypad_door_item":1,"piratesandlootersreborn:illager_silver_bar":1,"minecraft:smoker":8,"minecraft:item_frame":1,"travelersbackpack:iron_tier_upgrade":2,"mcwfurnitures:spruce_stool_chair":1,"securitycraft:sand_mine":1,"glass_doors_and_trapdoors:black_stained_glass_trapdoor":39,"minecraft:crafting_table":22,"minecraft:spruce_planks":788,"minecraft:baked_potato":530,"minecraft:iron_helmet":8,"minecraft:birch_planks":380,"rechiseled:chisel":3,"minecraft:dark_oak_slab":54,"minecraft:iron_chestplate":8,"minecraft:paper":12,"minecraft:diamond_pickaxe":2,"minecraft:shield":5,"minecraft:stick":680,"storagedrawers:fill_level_upgrade":32,"minecraft:iron_ingot":866,"minecraft:stone_sword":2,"minecraft:redstone_torch":157,"minecraft:shears":5,"securitycraft:universal_block_reinforcer_lvl1":5,"mcwdoors:garage_gray_door":8,"dawnoftimebuilder:big_flower_pot":2,"minecraft:redstone":18,"securitycraft:furnace_mine":3,"minecraft:coal":342,"glass_doors_and_trapdoors:glass_trapdoor":6,"storagedrawers:quantify_key":1,"minecraft:furnace":34,"minecraft:stone_button":9,"minecraft:blast_furnace":2,"additional_lights:fire_pit_l_smooth_stone":8,"minecraft:piston":37,"minecraft:gray_dye":2,"securitycraft:keypad_frame":1,"dawnoftimebuilder:spruce_support_slab":6,"minecraft:glass_pane":112,"minecraft:leather":2,"dawnoftimebuilder:spruce_planks_edge":114,"minecraft:black_terracotta":8,"minecraft:iron_axe":5,"betteranimalsplus:goatcheese":12,"minecraft:iron_hoe":2,"dawnoftimebuilder:iron_plate_armor_head":1,"dawnoftimebuilder:boxwood_small_hedge":96,"storagedrawers:spruce_full_drawers_1":1,"mcwfurnitures:spruce_table":6,"minecraft:cooked_beef":15,"minecraft:red_dye":6,"minecraft:cooked_cod":2,"elevatorid:elevator_white":3,"minecraft:spruce_sign":6,"travelersbackpack:backpack_tank":4,"minecraft:iron_sword":12,"minecraft:cooked_salmon":1,"minecraft:bucket":3,"minecraft:bread":29,"minecraft:air":0,"gobber2:gobber2_staff_ensnarement":1,"securitycraft:dirt_mine":10,"minecraft:blue_dye":86,"dawnoftimebuilder:paper_folding_screen":4,"minecraft:oak_boat":1,"minecraft:white_wool":24,"minecraft:gold_nugget":9,"minecraft:white_dye":1,"minecraft:anvil":1,"minecraft:torch":736,"minecraft:clay":17},"minecraft:used":{"minecraft:ladder":39,"minecraft:chest":35,"minecraft:stone":11,"dawnoftimebuilder:red_paper_lantern":16,"minecraft:rotten_flesh":201,"valhelsia_structures:cyan_glazed_jar":1,"securitycraft:keypad_item":5,"rechiseled:birch_planks_rotated_bricks":1,"minecraft:snowball":16,"minecraft:spruce_boat":17,"dawnoftimebuilder:spruce_planks_edge":117,"minecraft:lava_bucket":6,"betteranimalsplus:eel_meat_cooked":23,"minecraft:birch_sapling":8,"rechiseled:birch_planks_beams_connecting":62,"minecraft:bow":141,"minecraft:dark_oak_boat":1,"rechiseled:stone_small_tiles":2,"minecraft:furnace":30,"minecraft:cooked_cod":14,"additional_lights:fire_pit_l_smooth_stone":15,"mcwfurnitures:spruce_end_table":4,"minecraft:potato":1209,"additional_lights:fire_for_fire_pit_s":2,"valhelsia_structures:spruce_post":3,"minecraft:diorite":112,"rechiseled:birch_planks_mosaic":327,"minecraft:red_stained_glass":22,"valhelsia_structures:big_cyan_glazed_jar":2,"securitycraft:door_indestructible_iron_item":1,"minecraft:powered_rail":4,"securitycraft:reinforced_sand":12,"valhelsia_structures:big_black_glazed_jar":1,"securitycraft:keypad_frame":1,"minecraft:composter":17,"minecraft:golden_apple":2,"elevatorid:elevator_white":11,"minecraft:sand":634,"securitycraft:reinforced_blue_stained_glass":777,"glass_doors_and_trapdoors:glass_trapdoor":12,"minecraft:blast_furnace":7,"securitycraft:universal_block_remover":523,"dawnoftimebuilder:boxwood_tall_hedge":56,"mcwdoors:garage_black_door":39,"minecraft:birch_slab":8,"valhelsia_structures:big_red_glazed_jar":1,"minecraft:stone_button":1,"securitycraft:mine":2,"minecraft:smithing_table":4,"minecraft:birch_log":95,"minecraft:oak_boat":1,"minecraft:iron_bars":7,"mcwfurnitures:spruce_glass_table":2,"minecraft:cooked_salmon":9,"storagedrawers:spruce_half_drawers_4":3,"minecraft:torch":999,"minecraft:anvil":2,"minecraft:polished_diorite":16,"minecraft:iron_axe":396,"carryon:entity_item":22,"rechiseled:stone_smooth_tiles":8,"securitycraft:dirt_mine":14,"dawnoftimebuilder:rice":1,"betteranimalsplus:venisoncooked":7,"betteranimalsplus:goatmilk":1,"glass_doors_and_trapdoors:black_stained_glass_trapdoor":61,"minecraft:wheat_seeds":506,"minecraft:water_bucket":503,"storagedrawers:spruce_full_drawers_4":41,"minecraft:gold_ore":3,"minecraft:rail":5,"minecraft:oak_slab":2,"minecraft:crafting_table":32,"iceandfire:pixie_jar_2":1,"minecraft:spruce_log":214,"minecraft:oak_log":48,"minecraft:diamond_pickaxe":1708,"travelersbackpack:bookshelf":31,"betteranimalsplus:goatcheese":12,"minecraft:iron_pickaxe":13929,"travelersbackpack:white_sleeping_bag":1,"minecraft:spruce_trapdoor":1,"minecraft:spruce_sapling":17,"rechiseled:stone_smooth_tiles_connecting":10,"minecraft:cobblestone":559,"additional_lights:al_torch_stone_bricks":53,"travelersbackpack:standard":34,"minecraft:cooked_porkchop":12,"minecraft:iron_shovel":3598,"gobber2:gobber2_gooey_bread":2,"minecraft:shield":263,"minecraft:iron_sword":1919,"securitycraft:reinforced_polished_diorite":1064,"mcwdoors:garage_white_door":8,"minecraft:carrot":561,"minecraft:obsidian":1,"minecraft:lantern":107,"securitycraft:reinforced_polished_diorite_stairs":102,"minecraft:stone_bricks":1,"minecraft:item_frame":4,"rechiseled:granite_squares_connecting":8,"carryon:tile_item":25,"minecraft:repeater":77,"minecraft:red_carpet":8,"minecraft:hay_block":1,"minecraft:beetroot_seeds":967,"travelersbackpack:enderman":1,"iceandfire:pixie_jar_empty":2,"rechiseled:granite_brick_paving_connecting":406,"travelersbackpack:spider":16,"minecraft:stone_pickaxe":131,"minecraft:sandstone":6,"minecraft:redstone_block":19,"minecraft:sugar_cane":175,"minecraft:white_wool":3,"dawnoftimebuilder:commelina":1,"mcwfurnitures:spruce_stool_chair":2,"minecraft:black_bed":12,"minecraft:shears":18,"minecraft:redstone_torch":19,"minecraft:lever":18,"minecraft:dark_oak_log":239,"minecraft:bread":97,"valhelsia_structures:doused_torch":2,"minecraft:gravel":23,"storagedrawers:quantify_key":32,"betteranimalsplus:eel_meat_raw":1,"rechiseled:stone_small_tiles_connecting":16,"minecraft:cooked_rabbit":3,"minecraft:andesite":314,"minecraft:bone_meal":193,"minecraft:experience_bottle":4,"mcwdoors:garage_gray_door":8,"minecraft:stone_shovel":588,"minecraft:redstone":201,"minecraft:spruce_planks":1,"dawnoftimebuilder:cypress":2,"securitycraft:keypad_door_item":3,"rechiseled:dirt_blobs_connecting":3,"betteranimalsplus:fried_egg":6,"dawnoftimebuilder:big_flower_pot":2,"minecraft:stone_hoe":139,"dawnoftimebuilder:paper_folding_screen":7,"minecraft:dirt":1136,"minecraft:white_carpet":1,"minecraft:hopper":17,"elevatorid:elevator_blue":11,"dawnoftimebuilder:maple_red_sapling":4,"minecraft:granite":64,"minecraft:iron_hoe":252,"gobber2:gobber2_gooey_beef":1,"securitycraft:sand_mine":1,"minecraft:minecart":1,"piratesandlootersreborn:coconut":3,"minecraft:cooked_beef":15,"rechiseled:stone_small_bricks_connecting":291,"minecraft:cooked_mutton":7,"minecraft:baked_potato":454,"minecraft:spruce_sign":10,"securitycraft:iron_mine":1,"minecraft:cobblestone_slab":9,"rechiseled:granite_rotated_bricks_connecting":8,"minecraft:terracotta":1,"securitycraft:furnace_mine":3,"minecraft:painting":39,"minecraft:smoker":10,"piratesandlootersreborn:rom":1,"minecraft:piston":52,"minecraft:flower_pot":6,"minecraft:apple":16,"minecraft:stone_slab":6,"rechiseled:cobblestone_chiseled_border_connecting":734,"rechiseled:stone_smooth_brick_paving":354,"minecraft:bucket":517,"minecraft:sea_pickle":4,"storagedrawers:drawer_key":72,"minecraft:splash_potion":1,"minecraft:birch_stairs":5},"minecraft:custom":{"minecraft:interact_with_crafting_table":483,"minecraft:open_barrel":44,"goblintraders:trade_with_goblin":407,"minecraft:bell_ring":23,"minecraft:leave_game":65,"minecraft:time_since_death":540882,"minecraft:damage_blocked_by_shield":320,"minecraft:deaths":52,"minecraft:jump":22935,"minecraft:enchant_item":7,"minecraft:interact_with_furnace":464,"minecraft:sleep_in_bed":65,"minecraft:waystone_activated":5,"minecraft:damage_dealt":80290,"minecraft:interact_with_smoker":71,"minecraft:use_cauldron":2,"minecraft:horse_one_cm":17076,"minecraft:interact_with_smithing_table":14,"minecraft:interact_with_anvil":6,"minecraft:inspect_hopper":17,"minecraft:sneak_time":38484,"minecraft:interact_with_blast_furnace":63,"minecraft:time_since_rest":141271,"minecraft:swim_one_cm":1737453,"minecraft:fly_one_cm":2579304,"minecraft:open_chest":1613,"minecraft:fall_one_cm":459779,"minecraft:sprint_one_cm":3150221,"minecraft:drop":417,"minecraft:talked_to_villager":16,"minecraft:interact_with_brewingstand":1,"minecraft:walk_on_water_one_cm":964609,"minecraft:play_one_minute":3080108,"minecraft:player_kills":5,"minecraft:crouch_one_cm":62200,"minecraft:mob_kills":490,"minecraft:interact_with_campfire":12,"minecraft:climb_one_cm":100749,"minecraft:walk_one_cm":7736147,"minecraft:walk_under_water_one_cm":943516,"minecraft:boat_one_cm":3139542,"minecraft:pot_flower":1,"minecraft:interact_with_grindstone":3,"minecraft:damage_taken":51463,"minecraft:damage_absorbed":80,"minecraft:minecart_one_cm":6822},"minecraft:dropped":{"minecraft:iron_sword":6,"rechiseled:cobblestone_chiseled_border_connecting":36,"minecraft:lapis_lazuli":16,"minecraft:glass_bottle":1,"minecraft:diamond":18,"minecraft:crafting_table":1,"betteranimalsplus:blackbearhead_black":1,"minecraft:cracked_stone_bricks":4,"minecraft:saddle":1,"minecraft:rail":7,"minecraft:red_mushroom":7,"immersive_armors:warrior_boots":1,"minecraft:dirt":424,"minecraft:dark_oak_trapdoor":2,"rechiseled:andesite_bricks":1,"minecraft:gold_nugget":27,"minecraft:sand":11,"minecraft:sugar":8,"minecraft:iron_pickaxe":2,"minecraft:bone":15,"minecraft:stone_axe":1,"minecraft:compass":1,"minecraft:iron_nugget":18,"minecraft:stripped_dark_oak_log":1,"minecraft:rotten_flesh":19,"minecraft:oak_planks":1,"minecraft:tipped_arrow":1,"minecraft:leather_boots":2,"betteranimalsplus:antler":2,"minecraft:iron_ingot":19,"minecraft:wheat_seeds":8,"minecraft:feather":5,"minecraft:cobblestone":469,"minecraft:book":3,"minecraft:granite":2,"minecraft:coal":7,"minecraft:gray_wool":1,"minecraft:gray_bed":2,"minecraft:dead_bush":2,"minecraft:oak_stairs":2,"minecraft:red_dye":1,"minecraft:mossy_cobblestone_stairs":1,"minecraft:smooth_stone":1,"minecraft:paper":12,"minecraft:string":9,"minecraft:spruce_sapling":32,"minecraft:furnace":2,"betteranimalsplus:eel_meat_cooked":2,"minecraft:stone_sword":2,"minecraft:smooth_stone_slab":2,"minecraft:clay_ball":64,"minecraft:iron_boots":2,"minecraft:spruce_fence":2,"minecraft:lily_of_the_valley":2,"minecraft:diamond_sword":1,"minecraft:potato":1,"minecraft:stone":1,"minecraft:spruce_boat":1,"minecraft:flower_pot":2,"minecraft:sea_pickle":6,"minecraft:spruce_planks":82,"minecraft:spider_eye":2,"minecraft:stone_bricks":16,"minecraft:sandstone":2,"minecraft:bow":4,"minecraft:dark_prismarine":1,"minecraft:terracotta":1,"minecraft:gold_ore":3,"minecraft:spruce_sign":6,"minecraft:baked_potato":36,"minecraft:ender_pearl":2,"minecraft:dark_oak_sapling":1,"minecraft:lantern":7,"minecraft:leather":1,"valhelsia_structures:doused_torch":10,"minecraft:cod":1,"minecraft:flint":1,"minecraft:spruce_leaves":18,"gobber2:gobber2_gooey_bread_nether":2,"minecraft:mutton":5,"minecraft:cooked_cod":10,"piratesandlootersreborn:illager_silver_nugget":2,"minecraft:snowball":10,"gravestone:obituary":69,"betteranimalsplus:eel_meat_raw":3,"minecraft:gold_ingot":1,"minecraft:gravel":3,"minecraft:prismarine":2,"minecraft:cooked_mutton":1,"minecraft:stone_stairs":2,"minecraft:carrot":64,"travelersbackpack:white_sleeping_bag":1,"minecraft:beetroot_seeds":14,"iceandfire:pixie_dust":1,"minecraft:chest":2,"minecraft:iron_ore":1,"minecraft:arrow":4,"minecraft:stone_hoe":3,"minecraft:bread":11,"minecraft:mossy_cobblestone":1,"minecraft:minecart":1,"minecraft:poisonous_potato":12,"minecraft:tropical_fish":19,"minecraft:stick":4,"minecraft:diorite":4,"minecraft:torch":42,"betteranimalsplus:wolf_pelt_brown":1,"minecraft:iron_door":2,"travelersbackpack:enderman":2,"minecraft:iron_leggings":1,"minecraft:wither_rose":1,"minecraft:iron_axe":1,"dawnoftimebuilder:boxwood_bush":4,"securitycraft:mine":2,"minecraft:kelp":2,"storagedrawers:upgrade_template":3,"securitycraft:reinforced_polished_diorite_stairs":2,"minecraft:totem_of_undying":1,"dawnoftimebuilder:cypress":24,"minecraft:glass_pane":4,"minecraft:flint_and_steel":1,"securitycraft:universal_block_remover":1,"minecraft:shield":3,"dawnoftimebuilder:commelina":1,"minecraft:iron_chestplate":1,"minecraft:andesite":21,"minecraft:oak_sapling":12,"betteranimalsplus:venisonraw":1}},"DataVersion":2586}